crash_catcher/__init__.py
crash_catcher/__main__.py
crash_catcher/_version.py
crash_catcher/crash_catcher.py
crash_catcher-0.2.2.dist-info/LICENSE
crash_catcher-0.2.2.dist-info/WHEEL
crash_catcher-0.2.2.dist-info/METADATA
crash_catcher-0.2.2.dist-info/RECORD
